{
    "affinity": {
        "lucy": 28,
        "ardra": 4,
        "angga": 22,
        "mimo": 8
    },
    "dialogue_tracker": {
        "next_dialogue": {
            "lucy": "level_1.good.a",
            "angga": "level_1.neutral.a",
            "ardra": "level_0.good.a",
            "mimo": "level_0.good.a"
        },
        "current_mood": {
            "lucy": "neutral",
            "ardra": "neutral",
            "angga": "neutral",
            "mimo": "neutral"
        },
        "seen_variants": {
            "ardra_0_neutral": [
                "a"
            ],
            "ardra_0_good": [
                "a",
                "b"
            ],
            "ardra_1_good": [
                "a"
            ],
            "ardra_1_neutral": [
                "a"
            ],
            "ardra_1_bad": [
                "a"
            ],
            "ardra_0_bad": [
                "a"
            ],
            "lucy_0_neutral": [
                "a"
            ],
            "lucy_0_good": [
                "a"
            ],
            "lucy_1_neutral": [
                "a"
            ],
            "lucy_1_good": [
                "a"
            ],
            "lucy_2_neutral": [
                "a"
            ],
            "lucy_2_good": [
                "a"
            ],
            "mimo_0_neutral": [
                "a"
            ],
            "mimo_2_good": [
                "a"
            ],
            "mimo_1_neutral": [
                "a"
            ],
            "mimo_1_good": [
                "a"
            ],
            "angga_0_neutral": [
                "a",
                "b"
            ],
            "angga_0_good": [
                "a"
            ]
        }
    },
    "date_events": {
        "lucy:2": true
    }
}